README.md
pyproject.toml
pulumi_aws_native/__init__.py
pulumi_aws_native/_enums.py
pulumi_aws_native/_inputs.py
pulumi_aws_native/_utilities.py
pulumi_aws_native/cidr.py
pulumi_aws_native/extension_resource.py
pulumi_aws_native/get_account_id.py
pulumi_aws_native/get_azs.py
pulumi_aws_native/get_partition.py
pulumi_aws_native/get_region.py
pulumi_aws_native/get_ssm_parameter_list.py
pulumi_aws_native/get_ssm_parameter_string.py
pulumi_aws_native/get_url_suffix.py
pulumi_aws_native/import_value.py
pulumi_aws_native/outputs.py
pulumi_aws_native/provider.py
pulumi_aws_native/pulumi-plugin.json
pulumi_aws_native/py.typed
pulumi_aws_native.egg-info/PKG-INFO
pulumi_aws_native.egg-info/SOURCES.txt
pulumi_aws_native.egg-info/dependency_links.txt
pulumi_aws_native.egg-info/requires.txt
pulumi_aws_native.egg-info/top_level.txt
pulumi_aws_native/accessanalyzer/__init__.py
pulumi_aws_native/accessanalyzer/_inputs.py
pulumi_aws_native/accessanalyzer/analyzer.py
pulumi_aws_native/accessanalyzer/get_analyzer.py
pulumi_aws_native/accessanalyzer/outputs.py
pulumi_aws_native/acmpca/__init__.py
pulumi_aws_native/acmpca/_inputs.py
pulumi_aws_native/acmpca/certificate.py
pulumi_aws_native/acmpca/certificate_authority.py
pulumi_aws_native/acmpca/certificate_authority_activation.py
pulumi_aws_native/acmpca/get_certificate.py
pulumi_aws_native/acmpca/get_certificate_authority.py
pulumi_aws_native/acmpca/get_certificate_authority_activation.py
pulumi_aws_native/acmpca/outputs.py
pulumi_aws_native/acmpca/permission.py
pulumi_aws_native/amazonmq/__init__.py
pulumi_aws_native/amazonmq/configuration.py
pulumi_aws_native/amazonmq/get_configuration.py
pulumi_aws_native/amplify/__init__.py
pulumi_aws_native/amplify/_enums.py
pulumi_aws_native/amplify/_inputs.py
pulumi_aws_native/amplify/app.py
pulumi_aws_native/amplify/branch.py
pulumi_aws_native/amplify/domain.py
pulumi_aws_native/amplify/get_app.py
pulumi_aws_native/amplify/get_branch.py
pulumi_aws_native/amplify/get_domain.py
pulumi_aws_native/amplify/outputs.py
pulumi_aws_native/amplifyuibuilder/__init__.py
pulumi_aws_native/amplifyuibuilder/_enums.py
pulumi_aws_native/amplifyuibuilder/_inputs.py
